{
    "bank": {
        "item": [
            {
                "code": "102861100001",
                "text": "中国工商银行北京分行"
            },
            {
                "code": "102861100002",
                "text": "中国工商银行北京分行"
            },
            {
                "code": "102861100004",
                "text": "中国工商银行北京分行"
            },
            {
                "code": "102861200001",
                "text": "中国工商银行天津分行"
            },
            {
                "code": "102861200002",
                "text": "中国工商银行天津分行"
            },
            {
                "code": "102861200005",
                "text": "中国工商银行天津分行"
            },
            {
                "code": "102861300001",
                "text": "中国工商银行河北分行"
            },
            {
                "code": "102861300002",
                "text": "中国工商银行河北分行"
            },
            {
                "code": "102861300005",
                "text": "中国工商银行河北分行"
            },
            {
                "code": "102861400001",
                "text": "中国工商银行山西分行"
            },
            {
                "code": "102861400002",
                "text": "中国工商银行山西分行"
            },
            {
                "code": "102861400005",
                "text": "中国工商银行山西分行"
            },
            {
                "code": "102862100001",
                "text": "中国工商银行辽宁分行"
            },
            {
                "code": "102862100002",
                "text": "中国工商银行辽宁分行"
            },
            {
                "code": "102862100004",
                "text": "中国工商银行辽宁分行"
            },
            {
                "code": "102862200001",
                "text": "中国工商银行大连分行"
            },
            {
                "code": "102862200002",
                "text": "中国工商银行大连分行"
            },
            {
                "code": "102862200004",
                "text": "中国工商银行大连分行"
            },
            {
                "code": "102862300001",
                "text": "中国工商银行陕西分行"
            },
            {
                "code": "102862300002",
                "text": "中国工商银行陕西分行"
            },
            {
                "code": "102862300004",
                "text": "中国工商银行陕西分行"
            },
            {
                "code": "102862700001",
                "text": "中国工商银行湖北分行"
            },
            {
                "code": "102862700002",
                "text": "中国工商银行湖北分行"
            },
            {
                "code": "102862800001",
                "text": "中国工商银行四川分行"
            },
            {
                "code": "102862800002",
                "text": "中国工商银行四川分行"
            },
            {
                "code": "102862800005",
                "text": "中国工商银行四川分行"
            },
            {
                "code": "102863100001",
                "text": "中国工商银行上海分行"
            },
            {
                "code": "102863100002",
                "text": "中国工商银行上海分行"
            },
            {
                "code": "102863100005",
                "text": "中国工商银行上海分行"
            },
            {
                "code": "102863200001",
                "text": "中国工商银行江苏分行"
            },
            {
                "code": "102863200002",
                "text": "中国工商银行江苏分行"
            },
            {
                "code": "102863200005",
                "text": "中国工商银行江苏分行"
            },
            {
                "code": "102863300001",
                "text": "中国工商银行浙江分行"
            },
            {
                "code": "102863300002",
                "text": "中国工商银行浙江分行"
            },
            {
                "code": "102863300004",
                "text": "中国工商银行浙江分行"
            },
            {
                "code": "102863400001",
                "text": "中国工商银行苏州分行"
            },
            {
                "code": "102863400002",
                "text": "中国工商银行苏州分行"
            },
            {
                "code": "102863400005",
                "text": "中国工商银行苏州分行"
            },
            {
                "code": "102863500001",
                "text": "中国工商银行宁波分行"
            },
            {
                "code": "102863500002",
                "text": "中国工商银行宁波分行"
            },
            {
                "code": "102863500005",
                "text": "中国工商银行宁波分行"
            },
            {
                "code": "102863600001",
                "text": "中国工商银行安徽分行"
            },
            {
                "code": "102863600002",
                "text": "中国工商银行安徽分行"
            },
            {
                "code": "102863600004",
                "text": "中国工商银行安徽分行"
            },
            {
                "code": "102863700001",
                "text": "中国工商银行河南分行"
            },
            {
                "code": "102863700002",
                "text": "中国工商银行河南分行"
            },
            {
                "code": "102863700005",
                "text": "中国工商银行河南分行"
            },
            {
                "code": "102864100001",
                "text": "中国工商银行湖南分行"
            },
            {
                "code": "102864100002",
                "text": "中国工商银行湖南分行"
            },
            {
                "code": "102864100005",
                "text": "中国工商银行湖南分行"
            },
            {
                "code": "102864500001",
                "text": "中国工商银行黑龙江分行"
            },
            {
                "code": "102864500002",
                "text": "中国工商银行黑龙江分行"
            },
            {
                "code": "102864500004",
                "text": "中国工商银行黑龙江分行"
            },
            {
                "code": "102864800001",
                "text": "中国工商银行深圳分行"
            },
            {
                "code": "102864800002",
                "text": "中国工商银行深圳分行"
            },
            {
                "code": "102864800005",
                "text": "中国工商银行深圳分行"
            },
            {
                "code": "102865100001",
                "text": "中国工商银行广州分行"
            },
            {
                "code": "102865100002",
                "text": "中国工商银行广州分行"
            },
            {
                "code": "102865100004",
                "text": "中国工商银行广州分行"
            },
            {
                "code": "102865300001",
                "text": "中国工商银行山东分行"
            },
            {
                "code": "102865300002",
                "text": "中国工商银行山东分行"
            },
            {
                "code": "102866100001",
                "text": "中国工商银行重庆分行"
            },
            {
                "code": "102866100002",
                "text": "中国工商银行重庆分行"
            },
            {
                "code": "102866100005",
                "text": "中国工商银行重庆分行"
            },
            {
                "code": "103861100001",
                "text": "中国农业银行北京分行"
            },
            {
                "code": "103861100004",
                "text": "中国农业银行北京分行"
            },
            {
                "code": "103861200001",
                "text": "中国农业银行天津分行"
            },
            {
                "code": "103861200002",
                "text": "中国农业银行天津分行"
            },
            {
                "code": "103861300001",
                "text": "中国农业银行河北分行"
            },
            {
                "code": "103861300002",
                "text": "中国农业银行河北分行"
            },
            {
                "code": "103861400001",
                "text": "中国农业银行山西分行"
            },
            {
                "code": "103861400002",
                "text": "中国农业银行山西分行"
            },
            {
                "code": "103862100001",
                "text": "中国农业银行辽宁分行"
            },
            {
                "code": "103862100002",
                "text": "中国农业银行辽宁分行"
            },
            {
                "code": "103862200001",
                "text": "中国农业银行大连分行"
            },
            {
                "code": "103862200002",
                "text": "中国农业银行大连分行"
            },
            {
                "code": "103862300001",
                "text": "中国农业银行陕西分行"
            },
            {
                "code": "103862300002",
                "text": "中国农业银行陕西分行"
            },
            {
                "code": "103862700001",
                "text": "中国农业银行湖北分行"
            },
            {
                "code": "103862800001",
                "text": "中国农业银行四川分行"
            },
            {
                "code": "103862800003",
                "text": "中国农业银行四川分行"
            },
            {
                "code": "103863100001",
                "text": "中国农业银行上海分行"
            },
            {
                "code": "103863100003",
                "text": "中国农业银行上海分行"
            },
            {
                "code": "103863200001",
                "text": "中国农业银行江苏分行"
            },
            {
                "code": "103863200003",
                "text": "中国农业银行江苏分行"
            },
            {
                "code": "103863300001",
                "text": "中国农业银行浙江分行"
            },
            {
                "code": "103863300002",
                "text": "中国农业银行浙江分行"
            },
            {
                "code": "103863400001",
                "text": "中国农业银行苏州分行"
            },
            {
                "code": "103863400003",
                "text": "中国农业银行苏州分行"
            },
            {
                "code": "103863500001",
                "text": "中国农业银行宁波分行"
            },
            {
                "code": "103863500003",
                "text": "中国农业银行宁波分行"
            },
            {
                "code": "103863600001",
                "text": "中国农业银行安徽分行"
            },
            {
                "code": "103863600002",
                "text": "中国农业银行安徽分行"
            },
            {
                "code": "103863700001",
                "text": "中国农业银行河南分行"
            },
            {
                "code": "103863700003",
                "text": "中国农业银行河南分行"
            },
            {
                "code": "103864100001",
                "text": "中国农业银行湖南分行"
            },
            {
                "code": "103864100003",
                "text": "中国农业银行湖南分行"
            },
            {
                "code": "103864500001",
                "text": "中国农业银行黑龙江分行"
            },
            {
                "code": "103864500002",
                "text": "中国农业银行黑龙江分行"
            },
            {
                "code": "103864800001",
                "text": "中国农业银行深圳分行"
            },
            {
                "code": "103864800003",
                "text": "中国农业银行深圳分行"
            },
            {
                "code": "103865100001",
                "text": "中国农业银行广州分行"
            },
            {
                "code": "103865100003",
                "text": "中国农业银行广州分行"
            },
            {
                "code": "103865300001",
                "text": "中国农业银行山东分行"
            },
            {
                "code": "103866100001",
                "text": "中国农业银行重庆分行"
            },
            {
                "code": "103866100002",
                "text": "中国农业银行重庆分行"
            },
            {
                "code": "104861100001",
                "text": "中国银行北京分行"
            },
            {
                "code": "104861100002",
                "text": "中国银行北京分行"
            },
            {
                "code": "104861200001",
                "text": "中国银行天津分行"
            },
            {
                "code": "104861200003",
                "text": "中国银行天津分行"
            },
            {
                "code": "104861300001",
                "text": "中国银行河北支行"
            },
            {
                "code": "104861300002",
                "text": "中国银行河北分行"
            },
            {
                "code": "104861400001",
                "text": "中国银行山西分行"
            },
            {
                "code": "104861400003",
                "text": "中国银行山西分行"
            },
            {
                "code": "104862100001",
                "text": "中国银行辽宁分行"
            },
            {
                "code": "104862100002",
                "text": "中国银行辽宁分行"
            },
            {
                "code": "104862200001",
                "text": "中国银行大连分行"
            },
            {
                "code": "104862200002",
                "text": "中国银行大连分行"
            },
            {
                "code": "104862300001",
                "text": "中国银行陕西分行"
            },
            {
                "code": "104862300002",
                "text": "中国银行陕西分行"
            },
            {
                "code": "104862700001",
                "text": "中国银行湖北分行"
            },
            {
                "code": "104862800001",
                "text": "中国银行四川分行"
            },
            {
                "code": "104862800003",
                "text": "中国银行四川分行"
            },
            {
                "code": "104863100001",
                "text": "中国银行上海分行"
            },
            {
                "code": "104863100002",
                "text": "中国银行上海分行"
            },
            {
                "code": "104863200001",
                "text": "中国银行江苏分行"
            },
            {
                "code": "104863200002",
                "text": "中国银行江苏分行"
            },
            {
                "code": "104863300001",
                "text": "中国银行浙江分行"
            },
            {
                "code": "104863300002",
                "text": "中国银行浙江分行"
            },
            {
                "code": "104863400001",
                "text": "中国银行苏州分行"
            },
            {
                "code": "104863400003",
                "text": "中国银行苏州分行"
            },
            {
                "code": "104863500001",
                "text": "中国银行宁波分行"
            },
            {
                "code": "104863500003",
                "text": "中国银行宁波分行"
            },
            {
                "code": "104863600001",
                "text": "中国银行安徽分行"
            },
            {
                "code": "104863600002",
                "text": "中国银行安徽分行"
            },
            {
                "code": "104863700001",
                "text": "中国银行河南分行"
            },
            {
                "code": "104863700002",
                "text": "中国银行河南分行"
            },
            {
                "code": "104864100001",
                "text": "中国银行湖南分行"
            },
            {
                "code": "104864100002",
                "text": "中国银行湖南分行"
            },
            {
                "code": "104864500001",
                "text": "中国银行黑龙江分行"
            },
            {
                "code": "104864500002",
                "text": "中国银行黑龙江分行"
            },
            {
                "code": "104864800001",
                "text": "中国银行深圳分行"
            },
            {
                "code": "104864800003",
                "text": "中国银行深圳分行"
            },
            {
                "code": "104865100001",
                "text": "中国银行广州分行"
            },
            {
                "code": "104865100002",
                "text": "中国银行广州分行"
            },
            {
                "code": "104865300001",
                "text": "中国银行山东分行"
            },
            {
                "code": "104866100001",
                "text": "中国银行重庆分行"
            },
            {
                "code": "104866100002",
                "text": "中国银行重庆分行"
            },
            {
                "code": "105861100001",
                "text": "中国建设银行北京分行"
            },
            {
                "code": "105861100003",
                "text": "中国建设银行北京分行"
            },
            {
                "code": "105861200001",
                "text": "中国建设银行天津分行"
            },
            {
                "code": "105861200002",
                "text": "中国建设银行天津分行"
            },
            {
                "code": "105861300001",
                "text": "中国建设银行河北支行"
            },
            {
                "code": "105861300005",
                "text": "中国建设银行河北分行"
            },
            {
                "code": "105861400001",
                "text": "中国建设银行山西分行"
            },
            {
                "code": "105861400002",
                "text": "中国建设银行山西分行"
            },
            {
                "code": "105862100001",
                "text": "中国建设银行辽宁分行"
            },
            {
                "code": "105862100004",
                "text": "中国建设银行辽宁分行"
            },
            {
                "code": "105862200001",
                "text": "中国建设银行大连分行"
            },
            {
                "code": "105862200004",
                "text": "中国建设银行大连分行"
            },
            {
                "code": "105862300001",
                "text": "中国建设银行陕西分行"
            },
            {
                "code": "105862300002",
                "text": "中国建设银行陕西分行"
            },
            {
                "code": "105862700001",
                "text": "中国建设银行湖北分行"
            },
            {
                "code": "105862800001",
                "text": "中国建设银行四川分行"
            },
            {
                "code": "105862800004",
                "text": "中国建设银行四川分行"
            },
            {
                "code": "105863100001",
                "text": "中国建设银行上海分行"
            },
            {
                "code": "105863100002",
                "text": "中国建设银行上海分行"
            },
            {
                "code": "105863200001",
                "text": "中国建设银行江苏分行"
            },
            {
                "code": "105863200004",
                "text": "中国建设银行江苏分行"
            },
            {
                "code": "105863300001",
                "text": "中国建设银行浙江分行"
            },
            {
                "code": "105863300002",
                "text": "中国建设银行浙江分行"
            },
            {
                "code": "105863400001",
                "text": "中国建设银行苏州分行"
            },
            {
                "code": "105863400004",
                "text": "中国建设银行苏州分行"
            },
            {
                "code": "105863500001",
                "text": "中国建设银行宁波分行"
            },
            {
                "code": "105863500004",
                "text": "中国建设银行宁波分行"
            },
            {
                "code": "105863600001",
                "text": "中国建设银行安徽分行"
            },
            {
                "code": "105863600002",
                "text": "中国建设银行安徽分行"
            },
            {
                "code": "105863700001",
                "text": "中国建设银行河南分行"
            },
            {
                "code": "105863700004",
                "text": "中国建设银行河南分行"
            },
            {
                "code": "105864100001",
                "text": "中国建设银行湖南分行"
            },
            {
                "code": "105864100004",
                "text": "中国建设银行湖南分行"
            },
            {
                "code": "105864500001",
                "text": "中国建设银行黑龙江支行"
            },
            {
                "code": "105864500004",
                "text": "中国建设银行黑龙江分行"
            },
            {
                "code": "105864800001",
                "text": "中国建设银行深圳分行"
            },
            {
                "code": "105864800002",
                "text": "中国建设银行深圳分行"
            },
            {
                "code": "105865100001",
                "text": "中国建设银行广州分行"
            },
            {
                "code": "105865100002",
                "text": "中国建设银行广州分行"
            },
            {
                "code": "105865300001",
                "text": "中国建设银行山东分行"
            },
            {
                "code": "105866100001",
                "text": "中国建设银行重庆分行"
            },
            {
                "code": "105866100002",
                "text": "中国建设银行重庆分行"
            },
            {
                "code": "301861100001",
                "text": "交通银行北京分行"
            },
            {
                "code": "301861200001",
                "text": "交通银行天津分行"
            },
            {
                "code": "301861300001",
                "text": "交通银行河北分行"
            },
            {
                "code": "301861400001",
                "text": "交通银行山西分行"
            },
            {
                "code": "301862100001",
                "text": "交通银行辽宁分行"
            },
            {
                "code": "301862200001",
                "text": "交通银行大连分行"
            },
            {
                "code": "301862300001",
                "text": "交通银行陕西分行"
            },
            {
                "code": "301862700001",
                "text": "交通银行湖北分行"
            },
            {
                "code": "301862800001",
                "text": "交通银行四川分行"
            },
            {
                "code": "301863100001",
                "text": "交通银行上海分行"
            },
            {
                "code": "301863200001",
                "text": "交通银行江苏分行"
            },
            {
                "code": "301863300001",
                "text": "交通银行浙江分行"
            },
            {
                "code": "301863400001",
                "text": "交通银行苏州分行"
            },
            {
                "code": "301863500001",
                "text": "交通银行宁波分行"
            },
            {
                "code": "301863600001",
                "text": "交通银行安徽分行"
            },
            {
                "code": "301863700001",
                "text": "交通银行河南分行"
            },
            {
                "code": "301864100001",
                "text": "交通银行湖南分行"
            },
            {
                "code": "301864500001",
                "text": "交通银行黑龙江省分行"
            },
            {
                "code": "301864800001",
                "text": "交通银行深圳分行"
            },
            {
                "code": "301865100001",
                "text": "交通银行广州分行"
            },
            {
                "code": "301865300001",
                "text": "交通银行山东分行"
            },
            {
                "code": "301866100001",
                "text": "交通银行重庆分行"
            },
            {
                "code": "302864500001",
                "text": "中信银行信用卡黑龙江分行"
            },
            {
                "code": "303861400001",
                "text": "中国光大银行信用卡中心山西分行"
            },
            {
                "code": "303862700001",
                "text": "中国光大银行信用卡中心湖北分行"
            },
            {
                "code": "303865300001",
                "text": "中国光大银行信用卡中心山东分行"
            },
            {
                "code": "305861100001",
                "text": "中国民生银行北京分行"
            },
            {
                "code": "305861200001",
                "text": "中国民生银行天津分行"
            },
            {
                "code": "305861300001",
                "text": "中国民生银行河北分行"
            },
            {
                "code": "305861400001",
                "text": "中国民生银行山西分行"
            },
            {
                "code": "305862100001",
                "text": "中国民生银行辽宁分行"
            },
            {
                "code": "305862200001",
                "text": "中国民生银行大连分行"
            },
            {
                "code": "305862300001",
                "text": "中国民生银行陕西分行"
            },
            {
                "code": "305862700001",
                "text": "中国民生银行湖北分行"
            },
            {
                "code": "305862800001",
                "text": "中国民生银行四川分行"
            },
            {
                "code": "305863100001",
                "text": "中国民生银行上海分行"
            },
            {
                "code": "305863200001",
                "text": "中国民生银行江苏分行"
            },
            {
                "code": "305863300001",
                "text": "中国民生银行浙江分行"
            },
            {
                "code": "305863400001",
                "text": "中国民生银行苏州分行"
            },
            {
                "code": "305863500001",
                "text": "中国民生银行宁波分行"
            },
            {
                "code": "305863600001",
                "text": "中国民生银行安徽分行"
            },
            {
                "code": "305863700001",
                "text": "中国民生银行河南分行"
            },
            {
                "code": "305864100001",
                "text": "中国民生银行湖南分行"
            },
            {
                "code": "305864500001",
                "text": "中国民生银行黑龙江分行"
            },
            {
                "code": "305864800001",
                "text": "中国民生银行深圳分行"
            },
            {
                "code": "305865100001",
                "text": "中国民生银行广东分行"
            },
            {
                "code": "305865300001",
                "text": "中国民生银行山东分行"
            },
            {
                "code": "305866100001",
                "text": "中国民生银行重庆分行"
            },
            {
                "code": "306861100001",
                "text": "广东发展银行北京分行"
            },
            {
                "code": "306861200001",
                "text": "广东发展银行天津分行"
            },
            {
                "code": "306861300001",
                "text": "广东发展银行河北分行"
            },
            {
                "code": "306862200001",
                "text": "广东发展银行大连分行"
            },
            {
                "code": "306862300001",
                "text": "广东发展银行陕西分行"
            },
            {
                "code": "306863300001",
                "text": "广东发展银行浙江分行"
            },
            {
                "code": "306863400001",
                "text": "广东发展银行苏州分行"
            },
            {
                "code": "306863500001",
                "text": "广东发展银行宁波分行"
            },
            {
                "code": "306863700001",
                "text": "广东发展银行河南分行"
            },
            {
                "code": "306864100001",
                "text": "广东发展银行湖南分行"
            },
            {
                "code": "306864500001",
                "text": "广东发展银行黑龙江分行"
            },
            {
                "code": "306865100001",
                "text": "广东发展银行广东分行"
            },
            {
                "code": "306866100001",
                "text": "广东发展银行重庆分行"
            },
            {
                "code": "307861100001",
                "text": "深圳发展银行北京分行"
            },
            {
                "code": "307861200001",
                "text": "深圳发展银行天津分行"
            },
            {
                "code": "307861300001",
                "text": "深圳发展银行河北分行"
            },
            {
                "code": "307862200001",
                "text": "深圳发展银行大连分行"
            },
            {
                "code": "307862300001",
                "text": "深圳发展银行陕西分行"
            },
            {
                "code": "307862700001",
                "text": "深圳发展银行湖北分行"
            },
            {
                "code": "307863100001",
                "text": "深圳发展银行上海分行"
            },
            {
                "code": "307863300001",
                "text": "深圳发展银行浙江分行"
            },
            {
                "code": "307863400001",
                "text": "深圳发展银行苏州分行"
            },
            {
                "code": "307863500001",
                "text": "深圳发展银行宁波分行"
            },
            {
                "code": "307863600001",
                "text": "深圳发展银行安徽分行"
            },
            {
                "code": "307863700001",
                "text": "深圳发展银行河南分行"
            },
            {
                "code": "307864100001",
                "text": "深圳发展银行湖南分行"
            },
            {
                "code": "307864500001",
                "text": "深圳发展银行黑龙江分行"
            },
            {
                "code": "307864800001",
                "text": "深圳发展银行深圳分行"
            },
            {
                "code": "307865100001",
                "text": "深圳发展银行广东分行"
            },
            {
                "code": "307866100001",
                "text": "深圳发展银行重庆分行"
            },
            {
                "code": "308861100001",
                "text": "招商银行北京分行"
            },
            {
                "code": "308861100003",
                "text": "招商银行北京分行"
            },
            {
                "code": "308861200001",
                "text": "招商银行天津分行"
            },
            {
                "code": "308861200002",
                "text": "招商银行天津分行"
            },
            {
                "code": "308861300001",
                "text": "招商银行河北分行"
            },
            {
                "code": "308861300003",
                "text": "招商银行河北分行"
            },
            {
                "code": "308861400001",
                "text": "招商银行山西分行"
            },
            {
                "code": "308861400003",
                "text": "招商银行山西分行"
            },
            {
                "code": "308862100001",
                "text": "招商银行辽宁分行"
            },
            {
                "code": "308862100003",
                "text": "招商银行辽宁分行"
            },
            {
                "code": "308862200001",
                "text": "招商银行大连分行"
            },
            {
                "code": "308862200004",
                "text": "招商银行大连分行"
            },
            {
                "code": "308862300001",
                "text": "招商银行陕西分行"
            },
            {
                "code": "308862300003",
                "text": "招商银行陕西分行"
            },
            {
                "code": "308862700001",
                "text": "招商银行湖北分行"
            },
            {
                "code": "308862800001",
                "text": "招商银行四川分行"
            },
            {
                "code": "308862800003",
                "text": "招商银行四川分行"
            },
            {
                "code": "308863100001",
                "text": "招商银行上海分行"
            },
            {
                "code": "308863100003",
                "text": "招商银行上海分行"
            },
            {
                "code": "308863200001",
                "text": "招商银行江苏分行"
            },
            {
                "code": "308863200003",
                "text": "招商银行江苏分行"
            },
            {
                "code": "308863300001",
                "text": "招商银行浙江分行"
            },
            {
                "code": "308863300003",
                "text": "招商银行浙江分行"
            },
            {
                "code": "308863400001",
                "text": "招商银行苏州分行"
            },
            {
                "code": "308863400003",
                "text": "招商银行苏州分行"
            },
            {
                "code": "308863500001",
                "text": "招商银行宁波分行"
            },
            {
                "code": "308863500003",
                "text": "招商银行宁波分行"
            },
            {
                "code": "308863600001",
                "text": "招商银行安徽分行"
            },
            {
                "code": "308863600003",
                "text": "招商银行安徽分行"
            },
            {
                "code": "308863700001",
                "text": "招商银行河南分行"
            },
            {
                "code": "308863700003",
                "text": "招商银行河南分行"
            },
            {
                "code": "308864100001",
                "text": "招商银行湖南分行"
            },
            {
                "code": "308864100003",
                "text": "招商银行湖南分行"
            },
            {
                "code": "308864500001",
                "text": "招商银行黑龙江分行"
            },
            {
                "code": "308864500003",
                "text": "招商银行黑龙江分行"
            },
            {
                "code": "308864800001",
                "text": "招商银行深圳分行"
            },
            {
                "code": "308864800003",
                "text": "招商银行深圳分行"
            },
            {
                "code": "308865100001",
                "text": "招商银行广州分行"
            },
            {
                "code": "308865100003",
                "text": "招商银行广州分行"
            },
            {
                "code": "308865300001",
                "text": "招商银行山东分行"
            },
            {
                "code": "308866100001",
                "text": "招商银行重庆分行"
            },
            {
                "code": "308866100003",
                "text": "招商银行重庆分行"
            },
            {
                "code": "309861100001",
                "text": "兴业银行北京分行"
            },
            {
                "code": "309861100003",
                "text": "兴业银行北京分行"
            },
            {
                "code": "309861200001",
                "text": "兴业银行天津分行"
            },
            {
                "code": "309861200003",
                "text": "兴业银行天津分行"
            },
            {
                "code": "309861300001",
                "text": "兴业银行河北分行"
            },
            {
                "code": "309861300003",
                "text": "兴业银行河北分行"
            },
            {
                "code": "309861400001",
                "text": "兴业银行山西分行"
            },
            {
                "code": "309861400004",
                "text": "兴业银行山西分行"
            },
            {
                "code": "309862100001",
                "text": "兴业银行辽宁分行"
            },
            {
                "code": "309862100003",
                "text": "兴业银行辽宁分行"
            },
            {
                "code": "309862200001",
                "text": "兴业银行大连分行"
            },
            {
                "code": "309862200003",
                "text": "兴业银行大连分行"
            },
            {
                "code": "309862300001",
                "text": "兴业银行陕西分行"
            },
            {
                "code": "309862300003",
                "text": "兴业银行陕西分行"
            },
            {
                "code": "309862700001",
                "text": "兴业银行湖北分行"
            },
            {
                "code": "309862800001",
                "text": "兴业银行四川分行"
            },
            {
                "code": "309862800003",
                "text": "兴业银行四川分行"
            },
            {
                "code": "309863100001",
                "text": "兴业银行上海分行"
            },
            {
                "code": "309863100003",
                "text": "兴业银行上海分行"
            },
            {
                "code": "309863200001",
                "text": "兴业银行江苏分行"
            },
            {
                "code": "309863200003",
                "text": "兴业银行江苏分行"
            },
            {
                "code": "309863300001",
                "text": "兴业银行浙江分行"
            },
            {
                "code": "309863300003",
                "text": "兴业银行浙江分行"
            },
            {
                "code": "309863400001",
                "text": "兴业银行苏州分行"
            },
            {
                "code": "309863400003",
                "text": "兴业银行苏州分行"
            },
            {
                "code": "309863500001",
                "text": "兴业银行宁波分行"
            },
            {
                "code": "309863500003",
                "text": "兴业银行宁波分行"
            },
            {
                "code": "309863600001",
                "text": "兴业银行安徽分行"
            },
            {
                "code": "309863600003",
                "text": "兴业银行安徽分行"
            },
            {
                "code": "309863700001",
                "text": "兴业银行河南分行"
            },
            {
                "code": "309863700003",
                "text": "兴业银行河南分行"
            },
            {
                "code": "309864100001",
                "text": "兴业银行湖南分行"
            },
            {
                "code": "309864100003",
                "text": "兴业银行湖南分行"
            },
            {
                "code": "309864500001",
                "text": "兴业银行黑龙江分行"
            },
            {
                "code": "309864500003",
                "text": "兴业银行黑龙江分行"
            },
            {
                "code": "309864800001",
                "text": "兴业银行深圳分行"
            },
            {
                "code": "309864800003",
                "text": "兴业银行深圳分行"
            },
            {
                "code": "309865100001",
                "text": "兴业银行广东分行"
            },
            {
                "code": "309865100003",
                "text": "兴业银行广州分行"
            },
            {
                "code": "309865300001",
                "text": "兴业银行山东分行"
            },
            {
                "code": "309866100001",
                "text": "兴业银行重庆分行"
            },
            {
                "code": "309866100003",
                "text": "兴业银行重庆分行"
            },
            {
                "code": "310861100001",
                "text": "上海浦东发展银行北京分行"
            },
            {
                "code": "310861300001",
                "text": "上海浦东发展银行河北分行"
            },
            {
                "code": "310862200001",
                "text": "上海浦东发展银行大连分行"
            },
            {
                "code": "310862300001",
                "text": "上海浦东发展银行陕西分行"
            },
            {
                "code": "310862700001",
                "text": "上海浦东发展银行湖北分行"
            },
            {
                "code": "310863100001",
                "text": "上海浦东发展银行上海分行"
            },
            {
                "code": "310863300001",
                "text": "上海浦东发展银行浙江分行"
            },
            {
                "code": "310863400001",
                "text": "上海浦东发展银行苏州分行"
            },
            {
                "code": "310863500001",
                "text": "上海浦东发展银行宁波分行"
            },
            {
                "code": "310863600001",
                "text": "上海浦东发展银行安徽分行"
            },
            {
                "code": "310864100001",
                "text": "上海浦东发展银行湖南分行"
            },
            {
                "code": "310865300001",
                "text": "上海浦东发展银行山东分行"
            },
            {
                "code": "310866100001",
                "text": "上海浦东发展银行重庆分行"
            },
            {
                "code": "314861200001",
                "text": "农村商业银行天津分行"
            },
            {
                "code": "314861200002",
                "text": "农村商业银行天津分行"
            },
            {
                "code": "314863100001",
                "text": "农商行上海分行"
            },
            {
                "code": "314863200001",
                "text": "农商行江苏分行"
            },
            {
                "code": "314863600001",
                "text": "农商行安徽分行"
            },
            {
                "code": "314866100001",
                "text": "农商行重庆分行"
            },
            {
                "code": "317861100001",
                "text": "农村合作银行北京分行"
            },
            {
                "code": "317863200001",
                "text": "农村合作银行江苏分行"
            },
            {
                "code": "317863300001",
                "text": "农村合作银行浙江分行"
            },
            {
                "code": "318861200001",
                "text": "渤海银行天津分行"
            },
            {
                "code": "321861100001",
                "text": "北京银行北京分行"
            },
            {
                "code": "321861200001",
                "text": "北京银行天津分行"
            },
            {
                "code": "321862200001",
                "text": "北京银行大连分行"
            },
            {
                "code": "321862700001",
                "text": "北京银行湖北分行"
            },
            {
                "code": "321864100001",
                "text": "北京银行湖南分行"
            },
            {
                "code": "322861200001",
                "text": "天津银行天津分行"
            },
            {
                "code": "323861100001",
                "text": "乐山商行北京分行"
            },
            {
                "code": "324861100001",
                "text": "泉州银行北京分行"
            },
            {
                "code": "325861100001",
                "text": "宁波银行北京分行"
            },
            {
                "code": "325863300001",
                "text": "宁波银行浙江分行"
            },
            {
                "code": "325863500001",
                "text": "宁波银行宁波分公司"
            },
            {
                "code": "326861100001",
                "text": "南昌银行北京分行"
            },
            {
                "code": "327861100001",
                "text": "东莞银行北京分行"
            },
            {
                "code": "328861100001",
                "text": "绵阳商行北京分行"
            },
            {
                "code": "329863400001",
                "text": "苏州银行苏州分行"
            },
            {
                "code": "330861100001",
                "text": "平安银行北京分行"
            },
            {
                "code": "330861200001",
                "text": "平安银行天津分行"
            },
            {
                "code": "330862200001",
                "text": "平安银行大连分行"
            },
            {
                "code": "330862300001",
                "text": "平安银行陕西分行"
            },
            {
                "code": "330863300001",
                "text": "平安银行浙江分行"
            },
            {
                "code": "330863500001",
                "text": "平安银行宁波分行"
            },
            {
                "code": "330864100001",
                "text": "平安银行湖南分行"
            },
            {
                "code": "330864800001",
                "text": "平安银行深圳分行"
            },
            {
                "code": "330865100001",
                "text": "平安银行广东分行"
            },
            {
                "code": "330865300001",
                "text": "平安银行山东分行"
            },
            {
                "code": "330866100001",
                "text": "平安银行重庆分行"
            },
            {
                "code": "333864100001",
                "text": "华融湘江银行湖南分行"
            },
            {
                "code": "334861100001",
                "text": "中国光大银行北京分行"
            },
            {
                "code": "334861100004",
                "text": "中国光大银行北京分行"
            },
            {
                "code": "334861200001",
                "text": "中国光大银行天津分行"
            },
            {
                "code": "334861200004",
                "text": "中国光大银行天津分行"
            },
            {
                "code": "334861300001",
                "text": "中国光大银行河北分行"
            },
            {
                "code": "334861300004",
                "text": "中国光大银行河北分行"
            },
            {
                "code": "334861400001",
                "text": "中国光大银行山西分行"
            },
            {
                "code": "334861400004",
                "text": "中国光大银行山西分行"
            },
            {
                "code": "334862100001",
                "text": "中国光大银行辽宁分行"
            },
            {
                "code": "334862100004",
                "text": "中国光大银行辽宁分行"
            },
            {
                "code": "334862200001",
                "text": "中国光大银行大连分行"
            },
            {
                "code": "334862200004",
                "text": "中国光大银行大连分行"
            },
            {
                "code": "334862300001",
                "text": "中国光大银行陕西分行"
            },
            {
                "code": "334862300004",
                "text": "中国光大银行陕西分行"
            },
            {
                "code": "334862700001",
                "text": "中国光大银行武汉分行营业部"
            },
            {
                "code": "334862800001",
                "text": "中国光大银行四川分行"
            },
            {
                "code": "334862800004",
                "text": "中国光大银行四川分行"
            },
            {
                "code": "334863100001",
                "text": "中国光大银行上海分行"
            },
            {
                "code": "334863100004",
                "text": "中国光大银行上海分行"
            },
            {
                "code": "334863200001",
                "text": "中国光大银行江苏分行"
            },
            {
                "code": "334863200004",
                "text": "中国光大银行江苏分行"
            },
            {
                "code": "334863300001",
                "text": "中国光大银行浙江分行"
            },
            {
                "code": "334863300004",
                "text": "中国光大银行浙江分行"
            },
            {
                "code": "334863400001",
                "text": "中国光大银行苏州分行"
            },
            {
                "code": "334863400004",
                "text": "中国光大银行苏州分行"
            },
            {
                "code": "334863500001",
                "text": "中国光大银行宁波分行"
            },
            {
                "code": "334863500004",
                "text": "中国光大银行宁波分行"
            },
            {
                "code": "334863600001",
                "text": "中国光大银行安徽分行"
            },
            {
                "code": "334863600004",
                "text": "中国光大银行安徽分行"
            },
            {
                "code": "334863700001",
                "text": "中国光大银行河南分行"
            },
            {
                "code": "334863700004",
                "text": "中国光大银行河南分行"
            },
            {
                "code": "334864100001",
                "text": "中国光大银行湖南分行"
            },
            {
                "code": "334864100004",
                "text": "中国光大银行湖南分行"
            },
            {
                "code": "334864500001",
                "text": "中国光大银行黑龙江支行"
            },
            {
                "code": "334864500004",
                "text": "中国光大银行黑龙江分行"
            },
            {
                "code": "334864800001",
                "text": "中国光大银行深圳分行"
            },
            {
                "code": "334864800004",
                "text": "中国光大银行深圳分行"
            },
            {
                "code": "334865100001",
                "text": "中国光大银行广州分行"
            },
            {
                "code": "334865100004",
                "text": "中国光大银行广州分行"
            },
            {
                "code": "334865300001",
                "text": "中国光大银行山东分行"
            },
            {
                "code": "334866100001",
                "text": "中国光大银行重庆分行"
            },
            {
                "code": "334866100004",
                "text": "中国光大银行重庆分行"
            },
            {
                "code": "335861100001",
                "text": "中信银行北京分行"
            },
            {
                "code": "335861100002",
                "text": "中信银行北京分行"
            },
            {
                "code": "335861200001",
                "text": "中信银行天津分行"
            },
            {
                "code": "335861200002",
                "text": "中信银行天津分行"
            },
            {
                "code": "335861300001",
                "text": "中信银行河北分行"
            },
            {
                "code": "335861300002",
                "text": "中信银行河北分行"
            },
            {
                "code": "335861400001",
                "text": "中信银行山西分行"
            },
            {
                "code": "335861400002",
                "text": "中信银行山西分行"
            },
            {
                "code": "335862100001",
                "text": "中信银行辽宁分行"
            },
            {
                "code": "335862100002",
                "text": "中信银行辽宁分行"
            },
            {
                "code": "335862200001",
                "text": "中信银行大连分行"
            },
            {
                "code": "335862200002",
                "text": "中信银行大连分行"
            },
            {
                "code": "335862300001",
                "text": "中信银行陕西分行"
            },
            {
                "code": "335862300002",
                "text": "中信银行陕西分行"
            },
            {
                "code": "335862700001",
                "text": "中信银行湖北分行"
            },
            {
                "code": "335862800001",
                "text": "中信银行四川分行"
            },
            {
                "code": "335862800002",
                "text": "中信银行四川分行"
            },
            {
                "code": "335863100001",
                "text": "中信银行上海分行"
            },
            {
                "code": "335863100002",
                "text": "中信银行上海分行"
            },
            {
                "code": "335863200001",
                "text": "中信银行江苏分行"
            },
            {
                "code": "335863200002",
                "text": "中信银行江苏分行"
            },
            {
                "code": "335863300001",
                "text": "中信银行浙江分行"
            },
            {
                "code": "335863300002",
                "text": "中信银行浙江分行"
            },
            {
                "code": "335863400001",
                "text": "中信银行苏州分行"
            },
            {
                "code": "335863400002",
                "text": "中信银行苏州分行"
            },
            {
                "code": "335863500001",
                "text": "中信银行宁波分行"
            },
            {
                "code": "335863500002",
                "text": "中信银行宁波分行"
            },
            {
                "code": "335863600001",
                "text": "中信银行安徽分行"
            },
            {
                "code": "335863600002",
                "text": "中信银行安徽分行"
            },
            {
                "code": "335863700001",
                "text": "中信银行河南分行"
            },
            {
                "code": "335863700002",
                "text": "中信银行河南分行"
            },
            {
                "code": "335864100001",
                "text": "中信银行湖南分行"
            },
            {
                "code": "335864100002",
                "text": "中信银行湖南分行"
            },
            {
                "code": "335864500001",
                "text": "中信银行黑龙江分行"
            },
            {
                "code": "335864500002",
                "text": "中信银行黑龙江分行"
            },
            {
                "code": "335864800001",
                "text": "中信银行深圳分行"
            },
            {
                "code": "335864800002",
                "text": "中信银行深圳分行"
            },
            {
                "code": "335865100001",
                "text": "中信银行广州分行"
            },
            {
                "code": "335865100002",
                "text": "中信银行广州分行"
            },
            {
                "code": "335865300001",
                "text": "中信银行山东分行"
            },
            {
                "code": "335866100001",
                "text": "中信银行重庆分行"
            },
            {
                "code": "335866100002",
                "text": "中信银行重庆分行"
            },
            {
                "code": "336861100001",
                "text": "华夏银行北京分行"
            },
            {
                "code": "336861200002",
                "text": "华夏银行天津分行"
            },
            {
                "code": "336861300001",
                "text": "华夏银行河北分行"
            },
            {
                "code": "336862100001",
                "text": "华夏银行辽宁分行"
            },
            {
                "code": "336862200001",
                "text": "华夏银行大连分行"
            },
            {
                "code": "336862300001",
                "text": "华夏银行陕西分行"
            },
            {
                "code": "336862700001",
                "text": "华夏银行湖北分行"
            },
            {
                "code": "336862800001",
                "text": "华夏银行四川分行"
            },
            {
                "code": "336863100001",
                "text": "华夏银行上海分行"
            },
            {
                "code": "336863200001",
                "text": "华夏银行江苏分行"
            },
            {
                "code": "336863300001",
                "text": "华夏银行浙江分行"
            },
            {
                "code": "336863400001",
                "text": "华夏银行苏州分行"
            },
            {
                "code": "336863500001",
                "text": "华夏银行宁波分行"
            },
            {
                "code": "336863600001",
                "text": "华夏银行安徽分行"
            },
            {
                "code": "336864100001",
                "text": "华夏银行湖南分行"
            },
            {
                "code": "336865100001",
                "text": "华夏银行广东分行"
            },
            {
                "code": "336865300001",
                "text": "华夏银行山东分行"
            },
            {
                "code": "336866100001",
                "text": "华夏银行重庆分行"
            },
            {
                "code": "402862800001",
                "text": "农信社四川分行"
            },
            {
                "code": "403861100001",
                "text": "邮储银行北京分行"
            },
            {
                "code": "403861200001",
                "text": "邮储渠道天津分行"
            },
            {
                "code": "403861300001",
                "text": "邮储渠道河北分行"
            },
            {
                "code": "403861400001",
                "text": "邮储银行山西分行"
            },
            {
                "code": "403862100001",
                "text": "邮储渠道辽宁分行"
            },
            {
                "code": "403862200001",
                "text": "邮储银行大连分行"
            },
            {
                "code": "403862300001",
                "text": "邮储银行陕西分行"
            },
            {
                "code": "403862700001",
                "text": "邮储银行湖北分行"
            },
            {
                "code": "403862800001",
                "text": "邮储渠道四川分行"
            },
            {
                "code": "403863100001",
                "text": "邮储渠道上海分行"
            },
            {
                "code": "403863200001",
                "text": "邮储渠道江苏分行"
            },
            {
                "code": "403863300001",
                "text": "邮储银行浙江分行"
            },
            {
                "code": "403863400001",
                "text": "邮储渠道苏州分行"
            },
            {
                "code": "403863500001",
                "text": "邮储银行宁波分行"
            },
            {
                "code": "403863600001",
                "text": "邮政储蓄银行安徽分行"
            },
            {
                "code": "403863700001",
                "text": "邮储渠道河南分行"
            },
            {
                "code": "403864100001",
                "text": "邮储银行湖南分行"
            },
            {
                "code": "403864500001",
                "text": "邮储渠道黑龙江分行"
            },
            {
                "code": "403864800001",
                "text": "邮储银行深圳分行"
            },
            {
                "code": "403865100001",
                "text": "邮储银行广东分行"
            },
            {
                "code": "403865300001",
                "text": "邮储银行山东分行"
            },
            {
                "code": "403866100001",
                "text": "邮储渠道重庆分行"
            },
            {
                "code": "531861100001",
                "text": "花旗银行北京分行"
            },
            {
                "code": "531861200001",
                "text": "花旗银行天津分行"
            },
            {
                "code": "531862200001",
                "text": "花旗银行大连分行"
            },
            {
                "code": "531862800001",
                "text": "花旗银行四川分行"
            },
            {
                "code": "531863100001",
                "text": "花旗银行上海分行"
            },
            {
                "code": "531863200001",
                "text": "花旗银行江苏分行"
            },
            {
                "code": "531863300001",
                "text": "花旗银行浙江分行"
            },
            {
                "code": "531864100001",
                "text": "花旗银行湖南分行"
            },
            {
                "code": "531864800001",
                "text": "花旗银行深圳分行"
            },
            {
                "code": "531865100001",
                "text": "花旗银行广州分行"
            },
            {
                "code": "531866100001",
                "text": "花旗银行重庆分行"
            },
            {
                "code": "671861100001",
                "text": "渣打银行北京分行"
            },
            {
                "code": "800866100001",
                "text": "重庆医保"
            },
            {
                "code": "801861100001",
                "text": "齐商银行北京分行"
            },
            {
                "code": "811861100001",
                "text": "理财通66分行"
            },
            {
                "code": "821861100001",
                "text": "理财通168分行"
            },
            {
                "code": "831861100001",
                "text": "定活保365分行"
            },
            {
                "code": "832861100001",
                "text": "定活保33分行"
            }
        ]
    }
}